rtl/control/data_memory.sv
module data_memory #(
    parameter 
    A_WIDTH=20
) (
    input logic clk,
    input logic [31:0] A,
    input logic [31:0] WD,
    input logic WE,
    input logic [2:0] MemSrc,
    output logic [31:0] RD
);
    logic [7:0] data_mem_arr [2**A_WIDTH-1:0];
    logic [A_WIDTH-1:0] addr;
    assign addr = A[A_WIDTH-1:0];

    // only for the pdf
    initial $readmemh("test/gaussian.mem", data_mem_arr, 'h10000);

    // load 
    logic sign_bit;
    assign sign_bit = MemSrc[2] == 1 ? 1'b0 : data_mem_arr[addr][7]; // if MemSrc[2] == 1, then unsigned
    always_comb begin 
        if (MemSrc[1:0] == 2'b00)
            RD = {{24{sign_bit}}, data_mem_arr[addr]}; // LBU operation
        else if (MemSrc[1:0] == 2'b01)
            RD = {{16{sign_bit}}, data_mem_arr[addr + 1], data_mem_arr[addr]}; // LHU operation
        else
            RD = {data_mem_arr[addr + 3], data_mem_arr[addr + 2], data_mem_arr[addr + 1], data_mem_arr[addr]}; // LW operation
    end
    
    // store
    always_ff @(posedge clk)
        if (WE == 1) begin
            data_mem_arr[addr] <= WD[7:0];
            if (MemSrc[1:0] == 2'b01) data_mem_arr[addr + 1] <= WD[15:8]; // half word
            else if (MemSrc[1:0] == 2'b10) begin
                data_mem_arr[addr + 1] <= WD[15:8];
                data_mem_arr[addr + 2] <= WD[23:16];
                data_mem_arr[addr + 3] <= WD[31:24];
            end
        end
    
endmodule

rtl/alu/alu.sv
module alu #(
    parameter DATA_WIDTH = 32
)(
    input logic [DATA_WIDTH-1:0] op1,
    input logic [DATA_WIDTH-1:0] op2,
    input logic [2:0] ALUctrl,
    output logic [DATA_WIDTH-1:0] SUM,
    output logic zero,
)

    logic [DATA_WIDTH-1:0] tmpSum;

    assign EQ = op1 == op2;

    always_comb
        case ALUctrl
            3'b001: SUM = op1 - op2;
            3'b010: SUM = op1 & op2;
            3'b011: SUM = op1 | op2;
            default: SUM = op1 + op2;
        endcase

endmodule

rtl/alu/regfile.sv
module regfile #(
    parameter ADDRESS_WIDTH = 5,
    DATA_WIDTH = 32
)(
    input logic clk,
    input logic [ADDRESS_WIDTH-1:0] AD1,
    input logic [ADDRESS_WIDTH-1:0] AD2,
    input logic [ADDRESS_WIDTH-1:0] AD3,
    input logic WE3,
    input logic [DATA_WIDTH-1:0] WD3,
    output logic [DATA_WIDTH-1:0] a0,
    output logic [DATA_WIDTH-1:0] RD1,
    output logic [DATA_WIDTH-1:0] RD2
);

    logic [DATA_WIDTH-1:0] regs [2**ADDRESS_WIDTH-1:0];

    initial begin
        regs[0] = {DATA_WIDTH{1'b0}};
    end

    assign RD1 = regs[AD1];
    assign RD2 = regs[AD2];
    assign a0 = regs['h10];  // a0 made async **

    always_ff @(posedge clk) begin
        if(WE3 && AD3 != 0) regs[AD3] <= WD3;
    end

endmodule

rtl/control/extend.sv
module extend(
    input logic [31:7] Imm,
    input logic [2:0] ImmSrc,
    output logic [31:0] ImmExt
);

    logic msb;
    assign msb = Imm[31];

    always_comb 
        if (ImmSrc == 3'd1) ImmExt = {{19{msb}}, Imm[31], Imm[7], Imm[30:25], Imm[11:8], 1'b0}; // B Type Ins
        else if (ImmSrc == 3'd2) ImmExt = {{20{msb}}, Imm[31:25], Imm[11:7]}; // S Type Ins
        else if (ImmSrc == 3'd3) ImmExt = {{11{msb}}, Imm[31], Imm[19:12], Imm[20], Imm[30:21], 1'b0}; // J Type Ins
        else if (ImmSrc == 3'd4) ImmExt = {Imm[31:12], 12'b0}; // LUI Ins
        else ImmExt = {{20{msb}}, Imm[31:20]}; // Regular - corresponds to ImmSrc = 0, but for other possible signal values, Regular case will occur, in the case of an error
endmodule

rtl/control/control_unit.sv
module control_unit #(
) (
    input logic [6:0] op,
    input logic [2:0] funct3,
    input logic [6:0] funct7, 
    input logic Zero,

    output logic [1:0] PCSrc,
    output logic ResultSrc,
    output logic MemWrite,
    output logic [2:0] MemSrc,
    
    output logic [2:0] ALUControl,
    output logic ALUSrc,
    output logic [2:0] ImmSrc,
    output logic RegWrite,
    output logic RWSrc
);
    

    always_comb begin
        
        // 1. PCSrc: 0 for PC + 4, 1 for PC + Imm, 2 for RET
        case(op)
            7'b1101111: PCSrc = 2'b01; // JAL
            7'b1100011: PCSrc = Zero ? 2'b00 : 2'b01; // BNE
            7'b1100111: PCSrc = 2'b10; // JALR
            default: PCSrc = 2'b00;
        endcase
        

        // 2. ResultSrc: 1 read from Data MEM, else 0 (only LBU uses this)
        ResultSrc = (op == 7'b0000011) ? 1 : 0;

        // 3. MemWrite: 1 if write to Data MEM, else 0 (only SB uses this)
        MemWrite = (op == 7'b0100011) ? 1 : 0;

        // MemSrc = funct3 (just to make things clear)
        MemSrc = funct3;

        // 4. Reduced version of ALUControl to account for just 3 ins
        ALUControl = (op == 7'b0110111) ? 3'b010 : (funct7 == 7'b0100000 ? 3'b001 : 3'b000); // if LUI, then 010, else (if sub, then 001, else add (000))

        // 5. ALUSrc: 1 for Imm, 0 for rs2
        ALUSrc = (op == 7'b0000011 || op == 7'b0100011 || op == 7'b0010011 || op == 7'b0110111) ? 1 : 0; // LBU, SB, ADDI, LUI: 1 else 0
        
        // 6. ImmSrc 3 bits
        case(op)
            7'b1100011: ImmSrc = 1; // B Type Ins
            7'b0100011: ImmSrc = 2; // S Type Ins
            7'b1101111: ImmSrc = 3; // J Type Ins
            7'b0110111: ImmSrc = 4; // LUI Ins
            default: ImmSrc = 0; // Default
        endcase


        // 7. RegWrite: 1 if write to register else 0
        if (
            op == 7'b0110011 // add
            || op == 7'b0010011 // addi
            || op == 7'b0000011 // LB and other load ins
            || op == 7'b1100111 // JALR
            || op == 7'b1101111 // JAL
        ) RegWrite = 1;
        else RegWrite = 0;

        // 8: RWSrc: 1 if RegWrite Data = PC + 4 else 0
        RWSrc = (op == 7'b1100111 || op == 7'b1101111) ? 1 : 0;  // JAL & JALR 
    end
    
endmodule

rtl/control/instruction_memory.sv
module instruction_memory #(
    parameter A_WIDTH = 12
)(
    input logic [A_WIDTH-1:0] A,
    output logic [31:0] RD
);
    // byte addressing:
    logic [7:0] instr_arr [2**A_WIDTH-1:0];

    initial $readmemh("src/myprog/f1.s.hex", instr_arr);

    assign RD = {instr_arr[A+3], instr_arr[A+2], instr_arr[A+1], instr_arr[A]};
endmodule

rtl/pc/pc.sv
module pc#(
    parameter ADDRESS_WIDTH = 12
)(
    input logic clk,
    input logic rst,
    input logic [ADDRESS_WIDTH-1:0] pc_4,
    input logic [ADDRESS_WIDTH-1:0] pc_b,
    input logic [ADDRESS_WIDTH-1:0] pc_r,
    input logic [1:0] pc_src,
    output logic [ADDRESS_WIDTH-1:0] PC
);
    logic [ADDRESS_WIDTH-1:0] pc_next;

    // PC FF
    always_ff @(posedge clk, posedge rst)
       if(rst) PC <= {ADDRESS_WIDTH{1'b0}};
       else PC <= pc_next;

    // multiplexer
    always_comb
        case(pc_src)
            2'b1: pc_next = pc_b;
            2'b10: pc_next = pc_r;
            default: pc_next = pc_4;
        endcase

 endmodule

rtl/riscv_top.sv
module riscv_top#(
    parameter INS_ADDRESS_WIDTH = 12,
    DATA_WIDTH = 32
)(
    input logic clk,
    input logic rst,
    output logic [DATA_WIDTH-1:0] a0
);
    // pc wires
    logic [INS_ADDRESS_WIDTH-1:0] pc_val;
    logic [INS_ADDRESS_WIDTH-1:0] pc_incr_4;
    logic [INS_ADDRESS_WIDTH-1:0] pc_target;

    // instruction wires
    logic [DATA_WIDTH-1: 0] instr;

    // control signal wires
    logic [1:0] pc_src;
    logic result_src;
    logic mem_write;
    logic [2:0] mem_src;
    logic [2:0] alu_control;
    logic alu_src;
    logic [2:0] imm_src;
    logic reg_write;
    logic rw_src;

    // register file wires
    logic [DATA_WIDTH-1:0] rd1;
    logic [DATA_WIDTH-1:0] rd2;
    logic [DATA_WIDTH-1:0] wd3;

    // ALU wires
    logic zero;
    logic [DATA_WIDTH-1:0] imm_ext;
    logic [DATA_WIDTH-1:0] alu_result;
    logic [DATA_WIDTH-1:0] srcB;

    // data memory wires
    logic [DATA_WIDTH-1:0] read_data;
    logic [DATA_WIDTH-1:0] result;

    // MUXes for pc values 
    assign pc_incr_4 = pc_val + 0'b100;
    assign pc_target = pc_val + imm_ext[INS_ADDRESS_WIDTH-1:0];

    // MUX for ALU
    assign srcB = alu_src? imm_ext : rd2;

    // data memory MUX
    assign result = result_src? read_data : alu_result;

    // register file mux
    assign wd3 = rw_src? {{DATA_WIDTH-INS_ADDRESS_WIDTH{1'b0}}, pc_incr_4} : result;

    pc rv_pc(
        .clk(clk),
        .rst(rst),
        .pc_4(pc_incr_4),
        .pc_b(pc_target),
        .pc_r(alu_result[INS_ADDRESS_WIDTH-1:0]),
        .pc_src(pc_src),
        .PC(pc_val)
    );

    instruction_memory rv_ins_mem(
        .A(pc_val),
        .RD(instr)
    );

    control_unit rv_cu(
        .op(instr[6:0]),
        .funct3(instr[14:12]),
        .funct7(instr[31:25]),
        .Zero(zero),
        .PCSrc(pc_src),
        .ResultSrc(result_src),
        .MemWrite(mem_write),
        .MemSrc(mem_src),
        .ALUControl(alu_control),
        .ALUSrc(alu_src),
        .ImmSrc(imm_src),
        .RegWrite(reg_write),
        .RWSrc(rw_src)
    );

    extend rv_sign_ext(
        .Imm(instr[31:7]),
        .ImmSrc(imm_src),
        .ImmExt(imm_ext)
    );

    regfile rv_regfile(
        .clk(clk),
        .AD1(instr[19:15]),
        .AD2(instr[24:20]),
        .AD3(instr[11:7]),
        .WE3(reg_write),
        .WD3(wd3),
        .a0(a0),
        .RD1(rd1),
        .RD2(rd2)
    );

    alu rv_alu(
        .op1(rd1),
        .op2(srcB),
        .ALUctrl(alu_control),
        .SUM(alu_result),
        .zero(zero)
    );

    data_memory rv_data_mem(
        .clk(clk),
        .A(alu_result),
        .WD(rd2),
        .WE(mem_write),
        .MemSrc(mem_src),
        .RD(read_data)
    );

endmodule

test/F1Waveform.vcd
$version Generated by VerilatedVcd $end
$date Sun Dec  3 14:01:14 2023 $end
$timescale 1ps $end

 $scope module TOP $end
  $var wire 32 ` a0 [31:0] $end
  $var wire  1 ^ clk $end
  $var wire  1 _ rst $end
  $scope module riscv_top $end
   $var wire 32 h DATA_WIDTH [31:0] $end
   $var wire 32 g INS_ADDRESS_WIDTH [31:0] $end
   $var wire 32 ` a0 [31:0] $end
   $var wire  3 H alu_control [2:0] $end
   $var wire 32 R alu_result [31:0] $end
   $var wire  1 I alu_src $end
   $var wire  1 ^ clk $end
   $var wire 32 Q imm_ext [31:0] $end
   $var wire  3 J imm_src [2:0] $end
   $var wire 32 C instr [31:0] $end
   $var wire  3 G mem_src [2:0] $end
   $var wire  1 F mem_write $end
   $var wire 12 b pc_incr_4 [11:0] $end
   $var wire  2 D pc_src [1:0] $end
   $var wire 12 c pc_target [11:0] $end
   $var wire 12 a pc_val [11:0] $end
   $var wire 32 M rd1 [31:0] $end
   $var wire 32 N rd2 [31:0] $end
   $var wire 32 d read_data [31:0] $end
   $var wire  1 K reg_write $end
   $var wire 32 e result [31:0] $end
   $var wire  1 E result_src $end
   $var wire  1 _ rst $end
   $var wire  1 L rw_src $end
   $var wire 32 S srcB [31:0] $end
   $var wire 32 O wd3 [31:0] $end
   $var wire  1 P zero $end
   $scope module rv_alu $end
    $var wire  3 H ALUctrl [2:0] $end
    $var wire 32 h DATA_WIDTH [31:0] $end
    $var wire 32 R SUM [31:0] $end
    $var wire 32 M op1 [31:0] $end
    $var wire 32 S op2 [31:0] $end
    $var wire  1 P zero $end
   $upscope $end
   $scope module rv_cu $end
    $var wire  3 H ALUControl [2:0] $end
    $var wire  1 I ALUSrc $end
    $var wire  3 J ImmSrc [2:0] $end
    $var wire  3 G MemSrc [2:0] $end
    $var wire  1 F MemWrite $end
    $var wire  2 D PCSrc [1:0] $end
    $var wire  1 L RWSrc $end
    $var wire  1 K RegWrite $end
    $var wire  1 E ResultSrc $end
    $var wire  1 P Zero $end
    $var wire  3 G funct3 [2:0] $end
    $var wire  7 U funct7 [6:0] $end
    $var wire  7 T op [6:0] $end
   $upscope $end
   $scope module rv_data_mem $end
    $var wire 32 R A [31:0] $end
    $var wire 32 i A_WIDTH [31:0] $end
    $var wire  3 G MemSrc [2:0] $end
    $var wire 32 d RD [31:0] $end
    $var wire 32 N WD [31:0] $end
    $var wire  1 F WE $end
    $var wire 20 V addr [19:0] $end
    $var wire  1 ^ clk $end
    $var wire  1 W sign_bit $end
   $upscope $end
   $scope module rv_ins_mem $end
    $var wire 12 a A [11:0] $end
    $var wire 32 g A_WIDTH [31:0] $end
    $var wire 32 C RD [31:0] $end
   $upscope $end
   $scope module rv_pc $end
    $var wire 32 g ADDRESS_WIDTH [31:0] $end
    $var wire 12 a PC [11:0] $end
    $var wire  1 ^ clk $end
    $var wire 12 b pc_4 [11:0] $end
    $var wire 12 c pc_b [11:0] $end
    $var wire 12 f pc_next [11:0] $end
    $var wire 12 X pc_r [11:0] $end
    $var wire  2 D pc_src [1:0] $end
    $var wire  1 _ rst $end
   $upscope $end
   $scope module rv_regfile $end
    $var wire  5 Y AD1 [4:0] $end
    $var wire  5 Z AD2 [4:0] $end
    $var wire  5 [ AD3 [4:0] $end
    $var wire 32 j ADDRESS_WIDTH [31:0] $end
    $var wire 32 h DATA_WIDTH [31:0] $end
    $var wire 32 M RD1 [31:0] $end
    $var wire 32 N RD2 [31:0] $end
    $var wire 32 O WD3 [31:0] $end
    $var wire  1 K WE3 $end
    $var wire 32 ` a0 [31:0] $end
    $var wire  1 ^ clk $end
    $var wire 32 # regs[0] [31:0] $end
    $var wire 32 - regs[10] [31:0] $end
    $var wire 32 . regs[11] [31:0] $end
    $var wire 32 / regs[12] [31:0] $end
    $var wire 32 0 regs[13] [31:0] $end
    $var wire 32 1 regs[14] [31:0] $end
    $var wire 32 2 regs[15] [31:0] $end
    $var wire 32 3 regs[16] [31:0] $end
    $var wire 32 4 regs[17] [31:0] $end
    $var wire 32 5 regs[18] [31:0] $end
    $var wire 32 6 regs[19] [31:0] $end
    $var wire 32 $ regs[1] [31:0] $end
    $var wire 32 7 regs[20] [31:0] $end
    $var wire 32 8 regs[21] [31:0] $end
    $var wire 32 9 regs[22] [31:0] $end
    $var wire 32 : regs[23] [31:0] $end
    $var wire 32 ; regs[24] [31:0] $end
    $var wire 32 < regs[25] [31:0] $end
    $var wire 32 = regs[26] [31:0] $end
    $var wire 32 > regs[27] [31:0] $end
    $var wire 32 ? regs[28] [31:0] $end
    $var wire 32 @ regs[29] [31:0] $end
    $var wire 32 % regs[2] [31:0] $end
    $var wire 32 A regs[30] [31:0] $end
    $var wire 32 B regs[31] [31:0] $end
    $var wire 32 & regs[3] [31:0] $end
    $var wire 32 ' regs[4] [31:0] $end
    $var wire 32 ( regs[5] [31:0] $end
    $var wire 32 ) regs[6] [31:0] $end
    $var wire 32 * regs[7] [31:0] $end
    $var wire 32 + regs[8] [31:0] $end
    $var wire 32 , regs[9] [31:0] $end
   $upscope $end
   $scope module rv_sign_ext $end
    $var wire 25 \ Imm [31:7] $end
    $var wire 32 Q ImmExt [31:0] $end
    $var wire  3 J ImmSrc [2:0] $end
    $var wire  1 ] msb $end
   $upscope $end
  $upscope $end
 $upscope $end
$enddefinitions $end


#0
b00000000000000000000000000000000 #
b00000000000000000000000000000000 $
b00000000000000000000000000000000 %
b00000000000000000000000000000000 &
b00000000000000000000000000000000 '
b00000000000000000000000000000000 (
b00000000000000000000000000000000 )
b00000000000000000000000000000000 *
b00000000000000000000000000000000 +
b00000000000000000000000000000000 ,
b00000000000000000000000000000000 -
b00000000000000000000000000000000 .
b00000000000000000000000000000000 /
b00000000000000000000000000000000 0
b00000000000000000000000000000000 1
b00000000000000000000000000000000 2
b00000000000000000000000000000000 3
b00000000000000000000000000000000 4
b00000000000000000000000000000000 5
b00000000000000000000000000000000 6
b00000000000000000000000000000000 7
b00000000000000000000000000000000 8
b00000000000000000000000000000000 9
b00000000000000000000000000000000 :
b00000000000000000000000000000000 ;
b00000000000000000000000000000000 <
b00000000000000000000000000000000 =
b00000000000000000000000000000000 >
b00000000000000000000000000000000 ?
b00000000000000000000000000000000 @
b00000000000000000000000000000000 A
b00000000000000000000000000000000 B
b00000000000000000000000000000000 C
b00 D
0E
0F
b000 G
b000 H
0I
b000 J
0K
0L
b00000000000000000000000000000000 M
b00000000000000000000000000000000 N
b00000000000000000000000000000000 O
1P
b00000000000000000000000000000000 Q
b00000000000000000000000000000000 R
b00000000000000000000000000000000 S
b0000000 T
b0000000 U
b00000000000000000000 V
0W
b000000000000 X
b00000 Y
b00000 Z
b00000 [
b0000000000000000000000000 \
0]
1^
1_
b00000000000000000000000000000000 `
b000000000000 a
b000000000100 b
b000000000000 c
b00000000000000000000000000000000 d
b00000000000000000000000000000000 e
b000000000100 f
b00000000000000000000000000001100 g
b00000000000000000000000000100000 h
b00000000000000000000000000010100 i
b00000000000000000000000000000101 j
#1
b00000000000000000000010100010011 C
1I
1K
b0010011 T
b01010 [
b0000000000000000000001010 \
0^
#2
1^
#3
0^
#4
1^
#5
0^
#6
1^
0_
#7
0^
#8
b00000011000000000000010110010011 C
b00000000000000000000000000110000 O
0P
b00000000000000000000000000110000 Q
b00000000000000000000000000110000 R
b00000000000000000000000000110000 S
b0000001 U
b00000000000000110000 V
b000000110000 X
b10000 Z
b01011 [
b0000001100000000000001011 \
1^
b000000000100 a
b000000001000 b
b000000110100 c
b00000000000000000000000000110000 e
b000000001000 f
#9
0^
#10
b00000000000000000000000000110000 .
b00000000100000000000000011101111 C
b01 D
0I
b011 J
1L
b00000000000000000000000000001100 O
1P
b00000000000000000000000000001000 Q
b00000000000000000000000000000000 R
b00000000000000000000000000000000 S
b1101111 T
b0000000 U
b00000000000000000000 V
b000000000000 X
b01000 Z
b00001 [
b0000000010000000000000001 \
1^
b000000001000 a
b000000001100 b
b000000010000 c
b00000000000000000000000000000000 e
b000000010000 f
#11
0^
#12
b00000000000000000000000000001100 $
b11111111111101011000010110010011 C
b00 D
1I
b000 J
0L
b00000000000000000000000000110000 M
b00000000000000000000000000101111 O
0P
b11111111111111111111111111111111 Q
b00000000000000000000000000101111 R
b11111111111111111111111111111111 S
b0010011 T
b1111111 U
b00000000000000101111 V
b000000101111 X
b01011 Y
b11111 Z
b01011 [
b1111111111110101100001011 \
1]
1^
b000000010000 a
b000000010100 b
b000000001111 c
b00000000000000000000000000101111 e
b000000010100 f
#13
0^
#14
b00000000000000000000000000101111 .
b11111110000001011001111011100011 C
b01 D
b001 G
0I
b001 J
0K
b00000000000000000000000000101111 M
b11111111111111111111111111111100 Q
b00000000000000000000000000000000 S
b1100011 T
b00000 Z
b11101 [
b1111111000000101100111101 \
1^
b000000010100 a
b000000011000 b
b000000010000 c
b000000010000 f
#15
0^
#16
b11111111111101011000010110010011 C
b00 D
b000 G
1I
b000 J
1K
b00000000000000000000000000101110 O
b11111111111111111111111111111111 Q
b00000000000000000000000000101110 R
b11111111111111111111111111111111 S
b0010011 T
b00000000000000101110 V
b000000101110 X
b11111 Z
b01011 [
b1111111111110101100001011 \
1^
b000000010000 a
b000000010100 b
b000000001111 c
b00000000000000000000000000101110 e
b000000010100 f
#17
0^
#18
b00000000000000000000000000101110 .
b11111110000001011001111011100011 C
b01 D
b001 G
0I
b001 J
0K
b00000000000000000000000000101110 M
b11111111111111111111111111111100 Q
b00000000000000000000000000000000 S
b1100011 T
b00000 Z
b11101 [
b1111111000000101100111101 \
1^
b000000010100 a
b000000011000 b
b000000010000 c
b000000010000 f
#19
0^
#20
b11111111111101011000010110010011 C
b00 D
b000 G
1I
b000 J
1K
b00000000000000000000000000101101 O
b11111111111111111111111111111111 Q
b00000000000000000000000000101101 R
b11111111111111111111111111111111 S
b0010011 T
b00000000000000101101 V
b000000101101 X
b11111 Z
b01011 [
b1111111111110101100001011 \
1^
b000000010000 a
b000000010100 b
b000000001111 c
b00000000000000000000000000101101 e
b000000010100 f
#21
0^
#22
b00000000000000000000000000101101 .
b11111110000001011001111011100011 C
b01 D
b001 G
0I
b001 J
0K
b00000000000000000000000000101101 M
b11111111111111111111111111111100 Q
b00000000000000000000000000000000 S
b1100011 T
b00000 Z
b11101 [
b1111111000000101100111101 \
1^
b000000010100 a
b000000011000 b
b000000010000 c
b000000010000 f
#23
0^
#24
b11111111111101011000010110010011 C
b00 D
b000 G
1I
b000 J
1K
b00000000000000000000000000101100 O
b11111111111111111111111111111111 Q
b00000000000000000000000000101100 R
b11111111111111111111111111111111 S
b0010011 T
b00000000000000101100 V
b000000101100 X
b11111 Z
b01011 [
b1111111111110101100001011 \
1^
b000000010000 a
b000000010100 b
b000000001111 c
b00000000000000000000000000101100 e
b000000010100 f
#25
0^
#26
b00000000000000000000000000101100 .
b11111110000001011001111011100011 C
b01 D
b001 G
0I
b001 J
0K
b00000000000000000000000000101100 M
b11111111111111111111111111111100 Q
b00000000000000000000000000000000 S
b1100011 T
b00000 Z
b11101 [
b1111111000000101100111101 \
1^
b000000010100 a
b000000011000 b
b000000010000 c
b000000010000 f
#27
0^
#28
b11111111111101011000010110010011 C
b00 D
b000 G
1I
b000 J
1K
b00000000000000000000000000101011 O
b11111111111111111111111111111111 Q
b00000000000000000000000000101011 R
b11111111111111111111111111111111 S
b0010011 T
b00000000000000101011 V
b000000101011 X
b11111 Z
b01011 [
b1111111111110101100001011 \
1^
b000000010000 a
b000000010100 b
b000000001111 c
b00000000000000000000000000101011 e
b000000010100 f
#29
0^
#30
b00000000000000000000000000101011 .
b11111110000001011001111011100011 C
b01 D
b001 G
0I
b001 J
0K
b00000000000000000000000000101011 M
b11111111111111111111111111111100 Q
b00000000000000000000000000000000 S
b1100011 T
b00000 Z
b11101 [
b1111111000000101100111101 \
1^
b000000010100 a
b000000011000 b
b000000010000 c
b000000010000 f
#31
0^
#32
b11111111111101011000010110010011 C
b00 D
b000 G
1I
b000 J
1K
b00000000000000000000000000101010 O
b11111111111111111111111111111111 Q
b00000000000000000000000000101010 R
b11111111111111111111111111111111 S
b0010011 T
b00000000000000101010 V
b000000101010 X
b11111 Z
b01011 [
b1111111111110101100001011 \
1^
b000000010000 a
b000000010100 b
b000000001111 c
b00000000000000000000000000101010 e
b000000010100 f
#33
0^
#34
b00000000000000000000000000101010 .
b11111110000001011001111011100011 C
b01 D
b001 G
0I
b001 J
0K
b00000000000000000000000000101010 M
b11111111111111111111111111111100 Q
b00000000000000000000000000000000 S
b1100011 T
b00000 Z
b11101 [
b1111111000000101100111101 \
1^
b000000010100 a
b000000011000 b
b000000010000 c
b000000010000 f
#35
0^
#36
b11111111111101011000010110010011 C
b00 D
b000 G
1I
b000 J
1K
b00000000000000000000000000101001 O
b11111111111111111111111111111111 Q
b00000000000000000000000000101001 R
b11111111111111111111111111111111 S
b0010011 T
b00000000000000101001 V
b000000101001 X
b11111 Z
b01011 [
b1111111111110101100001011 \
1^
b000000010000 a
b000000010100 b
b000000001111 c
b00000000000000000000000000101001 e
b000000010100 f
#37
0^
#38
b00000000000000000000000000101001 .
b11111110000001011001111011100011 C
b01 D
b001 G
0I
b001 J
0K
b00000000000000000000000000101001 M
b11111111111111111111111111111100 Q
b00000000000000000000000000000000 S
b1100011 T
b00000 Z
b11101 [
b1111111000000101100111101 \
1^
b000000010100 a
b000000011000 b
b000000010000 c
b000000010000 f
#39
0^
#40
b11111111111101011000010110010011 C
b00 D
b000 G
1I
b000 J
1K
b00000000000000000000000000101000 O
b11111111111111111111111111111111 Q
b00000000000000000000000000101000 R
b11111111111111111111111111111111 S
b0010011 T
b00000000000000101000 V
b000000101000 X
b11111 Z
b01011 [
b1111111111110101100001011 \
1^
b000000010000 a
b000000010100 b
b000000001111 c
b00000000000000000000000000101000 e
b000000010100 f
#41
0^
#42
b00000000000000000000000000101000 .
b11111110000001011001111011100011 C
b01 D
b001 G
0I
b001 J
0K
b00000000000000000000000000101000 M
b11111111111111111111111111111100 Q
b00000000000000000000000000000000 S
b1100011 T
b00000 Z
b11101 [
b1111111000000101100111101 \
1^
b000000010100 a
b000000011000 b
b000000010000 c
b000000010000 f
#43
0^
#44
b11111111111101011000010110010011 C
b00 D
b000 G
1I
b000 J
1K
b00000000000000000000000000100111 O
b11111111111111111111111111111111 Q
b00000000000000000000000000100111 R
b11111111111111111111111111111111 S
b0010011 T
b00000000000000100111 V
b000000100111 X
b11111 Z
b01011 [
b1111111111110101100001011 \
1^
b000000010000 a
b000000010100 b
b000000001111 c
b00000000000000000000000000100111 e
b000000010100 f
#45
0^
#46
b00000000000000000000000000100111 .
b11111110000001011001111011100011 C
b01 D
b001 G
0I
b001 J
0K
b00000000000000000000000000100111 M
b11111111111111111111111111111100 Q
b00000000000000000000000000000000 S
b1100011 T
b00000 Z
b11101 [
b1111111000000101100111101 \
1^
b000000010100 a
b000000011000 b
b000000010000 c
b000000010000 f
#47
0^
#48
b11111111111101011000010110010011 C
b00 D
b000 G
1I
b000 J
1K
b00000000000000000000000000100110 O
b11111111111111111111111111111111 Q
b00000000000000000000000000100110 R
b11111111111111111111111111111111 S
b0010011 T
b00000000000000100110 V
b000000100110 X
b11111 Z
b01011 [
b1111111111110101100001011 \
1^
b000000010000 a
b000000010100 b
b000000001111 c
b00000000000000000000000000100110 e
b000000010100 f
#49
0^
#50
b00000000000000000000000000100110 .
b11111110000001011001111011100011 C
b01 D
b001 G
0I
b001 J
0K
b00000000000000000000000000100110 M
b11111111111111111111111111111100 Q
b00000000000000000000000000000000 S
b1100011 T
b00000 Z
b11101 [
b1111111000000101100111101 \
1^
b000000010100 a
b000000011000 b
b000000010000 c
b000000010000 f
#51
0^
#52
b11111111111101011000010110010011 C
b00 D
b000 G
1I
b000 J
1K
b00000000000000000000000000100101 O
b11111111111111111111111111111111 Q
b00000000000000000000000000100101 R
b11111111111111111111111111111111 S
b0010011 T
b00000000000000100101 V
b000000100101 X
b11111 Z
b01011 [
b1111111111110101100001011 \
1^
b000000010000 a
b000000010100 b
b000000001111 c
b00000000000000000000000000100101 e
b000000010100 f
#53
0^
#54
b00000000000000000000000000100101 .
b11111110000001011001111011100011 C
b01 D
b001 G
0I
b001 J
0K
b00000000000000000000000000100101 M
b11111111111111111111111111111100 Q
b00000000000000000000000000000000 S
b1100011 T
b00000 Z
b11101 [
b1111111000000101100111101 \
1^
b000000010100 a
b000000011000 b
b000000010000 c
b000000010000 f
#55
0^
#56
b11111111111101011000010110010011 C
b00 D
b000 G
1I
b000 J
1K
b00000000000000000000000000100100 O
b11111111111111111111111111111111 Q
b00000000000000000000000000100100 R
b11111111111111111111111111111111 S
b0010011 T
b00000000000000100100 V
b000000100100 X
b11111 Z
b01011 [
b1111111111110101100001011 \
1^
b000000010000 a
b000000010100 b
b000000001111 c
b00000000000000000000000000100100 e
b000000010100 f
#57
0^
#58
b00000000000000000000000000100100 .
b11111110000001011001111011100011 C
b01 D
b001 G
0I
b001 J
0K
b00000000000000000000000000100100 M
b11111111111111111111111111111100 Q
b00000000000000000000000000000000 S
b1100011 T
b00000 Z
b11101 [
b1111111000000101100111101 \
1^
b000000010100 a
b000000011000 b
b000000010000 c
b000000010000 f
#59
0^
#60
b11111111111101011000010110010011 C
b00 D
b000 G
1I
b000 J
1K
b00000000000000000000000000100011 O
b11111111111111111111111111111111 Q
b00000000000000000000000000100011 R
b11111111111111111111111111111111 S
b0010011 T
b00000000000000100011 V
b000000100011 X
b11111 Z
b01011 [
b1111111111110101100001011 \
1^
b000000010000 a
b000000010100 b
b000000001111 c
b00000000000000000000000000100011 e
b000000010100 f
#61
0^
#62
b00000000000000000000000000100011 .
b11111110000001011001111011100011 C
b01 D
b001 G
0I
b001 J
0K
b00000000000000000000000000100011 M
b11111111111111111111111111111100 Q
b00000000000000000000000000000000 S
b1100011 T
b00000 Z
b11101 [
b1111111000000101100111101 \
1^
b000000010100 a
b000000011000 b
b000000010000 c
b000000010000 f
#63
0^
#64
b11111111111101011000010110010011 C
b00 D
b000 G
1I
b000 J
1K
b00000000000000000000000000100010 O
b11111111111111111111111111111111 Q
b00000000000000000000000000100010 R
b11111111111111111111111111111111 S
b0010011 T
b00000000000000100010 V
b000000100010 X
b11111 Z
b01011 [
b1111111111110101100001011 \
1^
b000000010000 a
b000000010100 b
b000000001111 c
b00000000000000000000000000100010 e
b000000010100 f
#65
0^
#66
b00000000000000000000000000100010 .
b11111110000001011001111011100011 C
b01 D
b001 G
0I
b001 J
0K
b00000000000000000000000000100010 M
b11111111111111111111111111111100 Q
b00000000000000000000000000000000 S
b1100011 T
b00000 Z
b11101 [
b1111111000000101100111101 \
1^
b000000010100 a
b000000011000 b
b000000010000 c
b000000010000 f
#67
0^
#68
b11111111111101011000010110010011 C
b00 D
b000 G
1I
b000 J
1K
b00000000000000000000000000100001 O
b11111111111111111111111111111111 Q
b00000000000000000000000000100001 R
b11111111111111111111111111111111 S
b0010011 T
b00000000000000100001 V
b000000100001 X
b11111 Z
b01011 [
b1111111111110101100001011 \
1^
b000000010000 a
b000000010100 b
b000000001111 c
b00000000000000000000000000100001 e
b000000010100 f
#69
0^
#70
b00000000000000000000000000100001 .
b11111110000001011001111011100011 C
b01 D
b001 G
0I
b001 J
0K
b00000000000000000000000000100001 M
b11111111111111111111111111111100 Q
b00000000000000000000000000000000 S
b1100011 T
b00000 Z
b11101 [
b1111111000000101100111101 \
1^
b000000010100 a
b000000011000 b
b000000010000 c
b000000010000 f
#71
0^
